gong_math_utils/__init__.py
gong_math_utils/calc.py
gong_math_utils-0.1.0.dist-info/METADATA
gong_math_utils-0.1.0.dist-info/WHEEL
gong_math_utils-0.1.0.dist-info/RECORD
