Metadata-Version: 2.4
Name: gong-math-utils
Version: 0.1.0
Summary: example math utils
Author: hgim96715-lgtm
Author-email: hgim96715-lgtm@gmail.com
Requires-Python: >=3.10
Classifier: Programming Language :: Python :: 3
Classifier: Programming Language :: Python :: 3.10
Classifier: Programming Language :: Python :: 3.11
Classifier: Programming Language :: Python :: 3.12
Classifier: Programming Language :: Python :: 3.13
Classifier: Programming Language :: Python :: 3.14
